sendcm/__init__.py
sendcm/sendcm.py
sendcm-0.1.dist-info/LICENSE
sendcm-0.1.dist-info/METADATA
sendcm-0.1.dist-info/WHEEL
sendcm-0.1.dist-info/top_level.txt
sendcm-0.1.dist-info/RECORD
