Metadata-Version: 2.1
Name: sendcm
Version: 0.1
Summary: Python package to interact with the Send.cm API
Home-page: https://github.com/immodded/send-cm
Author: Modd
Author-email: immodded@proton.me
Classifier: Development Status :: 3 - Alpha
Classifier: Intended Audience :: Developers
Classifier: License :: OSI Approved :: MIT License
Classifier: Programming Language :: Python :: 3
Classifier: Programming Language :: Python :: 3.6
Classifier: Programming Language :: Python :: 3.7
Classifier: Programming Language :: Python :: 3.8
Classifier: Programming Language :: Python :: 3.9
License-File: LICENSE
Requires-Dist: requests
